{
    "FR-1234":{
        "name":"Fries Cooker",
        "type":"fries",
        "rate":15,
        "buycost":3000,
        "upgradecost":100
    },
    "ST-0000":{
        "name":"Orphan Obliterator",
        "type":"stan",
        "rate":20,
        "buycost":4000,
        "upgradecost":150
    },
    "CM-2000":{
        "name":"Crypto Miner 2000",
        "type":"gascoin",
        "rate":200,
        "buycost":7500,
        "upgradecost":6000
    },
    "KB-6969":{
        "name":"Kabi Drill",
        "type":"suppository",
        "rate":10,
        "buycost":6000,
        "upgradecost":150
    },
    "KM-1111":{
        "name":"Dickson Hammer",
        "type":"karma",
        "rate":20,
        "buycost":10000,
        "upgradecost":130
    }
}